mtool/__init__.py
mtool/convert.py
mtool/mtime.py
mtool/path.py
mtool-0.1.101.dist-info/licenses/LICENSE
mtool-0.1.101.dist-info/METADATA
mtool-0.1.101.dist-info/WHEEL
mtool-0.1.101.dist-info/top_level.txt
mtool-0.1.101.dist-info/RECORD
