Metadata-Version: 2.4
Name: mtool
Version: 0.1.101
Summary: A collection of utility tools for Python development
Author-email: Your Name <your.email@example.com>
License: MIT
Project-URL: Homepage, https://gitcode.com/pymod/mtool
Project-URL: Bug Tracker, https://gitcode.com/pymod/mtool/issues
Classifier: Programming Language :: Python :: 3
Classifier: License :: OSI Approved :: MIT License
Classifier: Operating System :: OS Independent
Classifier: Intended Audience :: Developers
Classifier: Topic :: Software Development :: Libraries :: Python Modules
Requires-Python: >=3.8
License-File: LICENSE
Requires-Dist: pytz>=2021.1
Requires-Dist: python-dateutil>=2.8.0
Provides-Extra: dev
Requires-Dist: pytest>=8.3.5; extra == "dev"
Dynamic: license-file
